yat_geo_db/__init__.py
yat_geo_db/fuzzy.py
yat_geo_db/geo_manager.py
yat_geo_db/geometry.py
yat_geo_db/settings.py
yat_geo_db/utils.py
yat_geo_db-1.1.2.dist-info/LICENSE
yat_geo_db-1.1.2.dist-info/METADATA
yat_geo_db-1.1.2.dist-info/WHEEL
yat_geo_db-1.1.2.dist-info/top_level.txt
yat_geo_db-1.1.2.dist-info/zip-safe
yat_geo_db-1.1.2.dist-info/RECORD
