Metadata-Version: 2.1
Name: yat_geo_db
Version: 1.1.2
Summary: A simple and effective Python wrapper around the Open Geo DB managed by YAT
Home-page: https://github.com/yat-co/yat-geo-db
Author: YAT, LLC
Author-email: Robert Goss <rgoss@yat.ai>, Jarod Hart <jhart@yat.ai>
License: The MIT License
Project-URL: Homepage, https://github.com/yat-co/yat-geo-db
Project-URL: Bug Tracker, https://github.com/yat-co/yat-geo-db/issues
Classifier: Programming Language :: Python :: 3
Classifier: License :: OSI Approved :: MIT License
Classifier: Operating System :: OS Independent
Requires-Python: >=3.7
License-File: LICENSE
Requires-Dist: requests
Requires-Dist: numpy
Requires-Dist: jellyfish
Requires-Dist: pytz
